setup.py
insight_sdk_linux.egg-info/PKG-INFO
insight_sdk_linux.egg-info/SOURCES.txt
insight_sdk_linux.egg-info/dependency_links.txt
insight_sdk_linux.egg-info/top_level.txt
insight_sdk_linux/com/__init__.py
insight_sdk_linux/com/data_handle.py
insight_sdk_linux/com/log_handle.py
insight_sdk_linux/com/insight/common.py
insight_sdk_linux/com/insight/market_service.py
insight_sdk_linux/com/insight/playback.py
insight_sdk_linux/com/insight/query.py
insight_sdk_linux/com/insight/subscribe.py
insight_sdk_linux/com/interface/mdc_gateway_base_define.py
insight_sdk_linux/com/interface/mdc_gateway_head.py
insight_sdk_linux/com/interface/mdc_gateway_interface.py
insight_sdk_linux/com/interface/mdc_recvdata_interface.py
insight_sdk_linux/com/__init__.py
insight_sdk_linux/com/data_handle.py
insight_sdk_linux/com/log_handle.py
insight_sdk_linux/com/cert/HTISCA.crt
insight_sdk_linux/com/cert/HTInsightCA.crt
insight_sdk_linux/com/cert/InsightClientCert.pem
insight_sdk_linux/com/cert/InsightClientKeyPkcs8.pem
insight_sdk_linux/com/insight/common.py
insight_sdk_linux/com/insight/market_service.py
insight_sdk_linux/com/insight/playback.py
insight_sdk_linux/com/insight/query.py
insight_sdk_linux/com/insight/subscribe.py
insight_sdk_linux/com/interface/mdc_gateway_base_define.py
insight_sdk_linux/com/interface/mdc_gateway_head.py
insight_sdk_linux/com/interface/mdc_gateway_interface.py
insight_sdk_linux/com/interface/mdc_recvdata_interface.py
insight_sdk_linux/com/libs/linux/python310/_mdc_gateway_client.so
insight_sdk_linux/com/libs/linux/python310/libACE.so.6.4.3
insight_sdk_linux/com/libs/linux/python310/libACE_SSL.so.6.4.3
insight_sdk_linux/com/libs/linux/python310/libmdc_query_client.so
insight_sdk_linux/com/libs/linux/python310/libprotobuf.so.11
insight_sdk_linux/com/libs/linux/python310/mdc_gateway_client.py
insight_sdk_linux/com/libs/linux/python36/_mdc_gateway_client.so
insight_sdk_linux/com/libs/linux/python36/libACE.so.6.4.3
insight_sdk_linux/com/libs/linux/python36/libACE_SSL.so.6.4.3
insight_sdk_linux/com/libs/linux/python36/libmdc_query_client.so
insight_sdk_linux/com/libs/linux/python36/libprotobuf.so.11
