Metadata-Version: 1.2
Name: insight-sdk-linux
Version: 4.0.7
Summary: insight_sdk_linux
Home-page: UNKNOWN
Author: htsc
Author-email: insight@htsc.com
License: insightpythonsdklinux
Project-URL: Documentation, https://packaging.python.org/tutorials/distributing-packages/
Project-URL: Funding, https://donate.pypi.org
Project-URL: Source, https://github.com/pypa/sampleproject/
Project-URL: Tracker, https://github.com/pypa/sampleproject/issues
Platform: UNKNOWN
Requires-Python: >=3.6.*
